LICENSE
purplepipes/.gitkeep
purplepipes/__init__.py
purplepipes-0.1.0.dist-info/LICENSE
purplepipes-0.1.0.dist-info/WHEEL
purplepipes-0.1.0.dist-info/METADATA
purplepipes-0.1.0.dist-info/RECORD
